LICENSE
MANIFEST.in
README.md
requirements.txt
run_little_brother_taskbar
setup.py
little_brother_taskbar/__init__.py
little_brother_taskbar/button_info.py
little_brother_taskbar/configuration_dialog.py
little_brother_taskbar/configuration_dialog_wxglade.py
little_brother_taskbar/configuration_model.py
little_brother_taskbar/constants.py
little_brother_taskbar/git.py
little_brother_taskbar/git_metadata.py
little_brother_taskbar/settings.py
little_brother_taskbar/status_connector.py
little_brother_taskbar/status_frame.py
little_brother_taskbar/status_frame_wxglade.py
little_brother_taskbar/taskbar.py
little_brother_taskbar/taskbar_app.py
little_brother_taskbar/user_status.py
little_brother_taskbar.egg-info/PKG-INFO
little_brother_taskbar.egg-info/SOURCES.txt
little_brother_taskbar.egg-info/dependency_links.txt
little_brother_taskbar.egg-info/requires.txt
little_brother_taskbar.egg-info/top_level.txt
little_brother_taskbar/static/icons/little-brother-taskbar-logo_128x128.png
little_brother_taskbar/static/icons/little-brother-taskbar-logo_32x32.bmp
little_brother_taskbar/static/icons/little-brother-taskbar-logo_32x32.png
little_brother_taskbar/templates/status_field.j2.html
little_brother_taskbar/test/__init__.py
little_brother_taskbar/test/test_suite.py
little_brother_taskbar/test/test_taskbar_app.py
little_brother_taskbar/translations/bn/LC_MESSAGES/messages.mo
little_brother_taskbar/translations/da/LC_MESSAGES/messages.mo
little_brother_taskbar/translations/de/LC_MESSAGES/messages.mo
little_brother_taskbar/translations/es/LC_MESSAGES/messages.mo
little_brother_taskbar/translations/fi/LC_MESSAGES/messages.mo
little_brother_taskbar/translations/fr/LC_MESSAGES/messages.mo
little_brother_taskbar/translations/it/LC_MESSAGES/messages.mo
little_brother_taskbar/translations/ja/LC_MESSAGES/messages.mo
little_brother_taskbar/translations/nl/LC_MESSAGES/messages.mo
little_brother_taskbar/translations/ru/LC_MESSAGES/messages.mo
little_brother_taskbar/translations/th/LC_MESSAGES/messages.mo
little_brother_taskbar/translations/tr/LC_MESSAGES/messages.mo