Metadata-Version: 2.1
Name: little-brother-taskbar
Version: 0.1.23
Summary: Taskbar app displaying the remaining play time of users monitored by LittleBrother
Home-page: https://github.com/marcus67/little_brother_taskbar
Author: Marcus Rickert
Author-email: little-brother@web.de
License: UNKNOWN
Platform: UNKNOWN
License-File: LICENSE
